{
    "id": 1862133451072,
    "scene_width": 64000,
    "scene_height": 64000,
    "nodes": [
        {
            "id": 1862133141168,
            "title": "Image Preview",
            "pos_x": 71.18749999999996,
            "pos_y": -309.875,
            "inputs": [
                {
                    "id": 1862133141312,
                    "index": 0,
                    "multi_edges": false,
                    "position": 3,
                    "socket_type": 5
                },
                {
                    "id": 1862133140064,
                    "index": 1,
                    "multi_edges": false,
                    "position": 3,
                    "socket_type": 6
                },
                {
                    "id": 1862133139920,
                    "index": 2,
                    "multi_edges": false,
                    "position": 3,
                    "socket_type": 1
                }
            ],
            "outputs": [
                {
                    "id": 1862133139968,
                    "index": 0,
                    "multi_edges": true,
                    "position": 6,
                    "socket_type": 5
                },
                {
                    "id": 1862133139872,
                    "index": 1,
                    "multi_edges": true,
                    "position": 6,
                    "socket_type": 6
                },
                {
                    "id": 1862133139776,
                    "index": 2,
                    "multi_edges": true,
                    "position": 6,
                    "socket_type": 1
                }
            ],
            "content": {
                "FPS": "24",
                "": "False"
            },
            "op_code": 28,
            "content_label_objname": "image_output_node"
        },
        {
            "id": 1862133139008,
            "title": "Kandinsky Text2Image",
            "pos_x": -801.8125,
            "pos_y": -356.875,
            "inputs": [],
            "outputs": [],
            "content": {},
            "op_code": 16,
            "content_label_objname": "bg_node",
            "color": "#ff5555ff",
            "width": 1393.1875,
            "height": 949.75
        },
        {
            "id": 1877383882992,
            "title": "Execute",
            "pos_x": -786.9375,
            "pos_y": -282.375,
            "inputs": [
                {
                    "id": 1877383883808,
                    "index": 0,
                    "multi_edges": false,
                    "position": 3,
                    "socket_type": 1
                }
            ],
            "outputs": [
                {
                    "id": 1877383883856,
                    "index": 0,
                    "multi_edges": true,
                    "position": 6,
                    "socket_type": 1
                }
            ],
            "content": {},
            "op_code": 19,
            "content_label_objname": "exec_node"
        },
        {
            "id": 1877383880736,
            "title": "Image Preview",
            "pos_x": 1116.7500000000002,
            "pos_y": -282.6875,
            "inputs": [
                {
                    "id": 1877383882128,
                    "index": 0,
                    "multi_edges": false,
                    "position": 3,
                    "socket_type": 5
                },
                {
                    "id": 1877383880016,
                    "index": 1,
                    "multi_edges": false,
                    "position": 3,
                    "socket_type": 6
                },
                {
                    "id": 1877383880112,
                    "index": 2,
                    "multi_edges": false,
                    "position": 3,
                    "socket_type": 1
                }
            ],
            "outputs": [
                {
                    "id": 1877383879968,
                    "index": 0,
                    "multi_edges": true,
                    "position": 6,
                    "socket_type": 5
                },
                {
                    "id": 1877383879728,
                    "index": 1,
                    "multi_edges": true,
                    "position": 6,
                    "socket_type": 6
                },
                {
                    "id": 1877383879680,
                    "index": 2,
                    "multi_edges": true,
                    "position": 6,
                    "socket_type": 1
                }
            ],
            "content": {
                "FPS": "24",
                "": "False"
            },
            "op_code": 28,
            "content_label_objname": "image_output_node"
        },
        {
            "id": 1862133139008,
            "title": "Kandinsky Image2Image",
            "pos_x": 626.25,
            "pos_y": -345.9375,
            "inputs": [],
            "outputs": [],
            "content": {},
            "op_code": 16,
            "content_label_objname": "bg_node",
            "color": "#ff5555ff",
            "width": 1161.0000000000002,
            "height": 966.0
        },
        {
            "id": 1601089257968,
            "title": "Kandinsky",
            "pos_x": -387.9875,
            "pos_y": -304.28749999999985,
            "inputs": [
                {
                    "id": 1601089227552,
                    "index": 0,
                    "multi_edges": false,
                    "position": 3,
                    "socket_type": 5
                },
                {
                    "id": 1601089229616,
                    "index": 1,
                    "multi_edges": false,
                    "position": 3,
                    "socket_type": 5
                },
                {
                    "id": 1601089226640,
                    "index": 2,
                    "multi_edges": false,
                    "position": 3,
                    "socket_type": 6
                },
                {
                    "id": 1601089234704,
                    "index": 3,
                    "multi_edges": false,
                    "position": 3,
                    "socket_type": 1
                }
            ],
            "outputs": [
                {
                    "id": 1601089240896,
                    "index": 0,
                    "multi_edges": true,
                    "position": 6,
                    "socket_type": 5
                },
                {
                    "id": 1601089226976,
                    "index": 1,
                    "multi_edges": false,
                    "position": 6,
                    "socket_type": 1
                }
            ],
            "content": {
                "Use Flash Attn": "False",
                "Use Finetune": "False",
                "Task": "TXT2IMG",
                "Tensor Preview": "False",
                "Prompt:": "",
                "Negative Prompt:": "",
                "Negative Prior Prompt:": "",
                "Seed:": "",
                "Steps:": "25",
                "Guidance Scale:": "4",
                "Width:": "512",
                "Height:": "512",
                "Strength:": "0.84",
                "Sampler:": "p_sampler",
                "Prior Scale:": "4",
                "Prior Steps:": "5",
                "Force Values:": "False"
            },
            "op_code": 58,
            "content_label_objname": "kandinsky_node"
        },
        {
            "id": 1601089227264,
            "title": "Kandinsky",
            "pos_x": 700.7812499999998,
            "pos_y": -251.796875,
            "inputs": [
                {
                    "id": 1601089226544,
                    "index": 0,
                    "multi_edges": false,
                    "position": 3,
                    "socket_type": 5
                },
                {
                    "id": 1601089234608,
                    "index": 1,
                    "multi_edges": false,
                    "position": 3,
                    "socket_type": 5
                },
                {
                    "id": 1601089233744,
                    "index": 2,
                    "multi_edges": false,
                    "position": 3,
                    "socket_type": 6
                },
                {
                    "id": 1601089240944,
                    "index": 3,
                    "multi_edges": false,
                    "position": 3,
                    "socket_type": 1
                }
            ],
            "outputs": [
                {
                    "id": 1601089234368,
                    "index": 0,
                    "multi_edges": true,
                    "position": 6,
                    "socket_type": 5
                },
                {
                    "id": 1601089233696,
                    "index": 1,
                    "multi_edges": false,
                    "position": 6,
                    "socket_type": 1
                }
            ],
            "content": {
                "Use Flash Attn": "False",
                "Use Finetune": "False",
                "Task": "TXT2IMG",
                "Tensor Preview": "False",
                "Prompt:": "",
                "Negative Prompt:": "",
                "Negative Prior Prompt:": "",
                "Seed:": "",
                "Steps:": "25",
                "Guidance Scale:": "4",
                "Width:": "512",
                "Height:": "512",
                "Strength:": "0.84",
                "Sampler:": "p_sampler",
                "Prior Scale:": "4",
                "Prior Steps:": "5",
                "Force Values:": "False"
            },
            "op_code": 58,
            "content_label_objname": "kandinsky_node"
        }
    ],
    "edges": [
        {
            "id": 1601089234080,
            "edge_type": 2,
            "start": 1877383883856,
            "end": 1601089234704
        },
        {
            "id": 1601089225536,
            "edge_type": 2,
            "start": 1601089226976,
            "end": 1862133139920
        },
        {
            "id": 1601089305904,
            "edge_type": 2,
            "start": 1601089240896,
            "end": 1862133141312
        },
        {
            "id": 1601089225968,
            "edge_type": 2,
            "start": 1862133139776,
            "end": 1601089240944
        },
        {
            "id": 1601089226016,
            "edge_type": 2,
            "start": 1862133139968,
            "end": 1601089234608
        },
        {
            "id": 1601089225920,
            "edge_type": 2,
            "start": 1877383880112,
            "end": 1601089233696
        },
        {
            "id": 1601089225872,
            "edge_type": 2,
            "start": 1601089234368,
            "end": 1877383882128
        }
    ]
}