{
    "id": 1599354920704,
    "scene_width": 64000,
    "scene_height": 64000,
    "nodes": [
        {
            "id": 1600670137264,
            "title": "Kandinsky Loader",
            "pos_x": 574.4934082031245,
            "pos_y": -1072.983398437499,
            "inputs": [
                {
                    "id": 1599361742688,
                    "index": 0,
                    "multi_edges": false,
                    "position": 3,
                    "socket_type": 1
                }
            ],
            "outputs": [
                {
                    "id": 1599340193408,
                    "index": 0,
                    "multi_edges": true,
                    "position": 6,
                    "socket_type": 4
                },
                {
                    "id": 1599340183712,
                    "index": 1,
                    "multi_edges": true,
                    "position": 6,
                    "socket_type": 4
                },
                {
                    "id": 1599340190000,
                    "index": 2,
                    "multi_edges": true,
                    "position": 6,
                    "socket_type": 4
                },
                {
                    "id": 1599354925888,
                    "index": 3,
                    "multi_edges": false,
                    "position": 6,
                    "socket_type": 1
                }
            ],
            "content": {},
            "op_code": 35,
            "content_label_objname": "kandinsky_loader_node"
        },
        {
            "id": 1599361730016,
            "title": "Kandinsky Conditioning Interpolation",
            "pos_x": 1171.2934082031252,
            "pos_y": -267.9833984374997,
            "inputs": [
                {
                    "id": 1598739664560,
                    "index": 0,
                    "multi_edges": false,
                    "position": 3,
                    "socket_type": 3
                },
                {
                    "id": 1598739662640,
                    "index": 1,
                    "multi_edges": false,
                    "position": 3,
                    "socket_type": 3
                },
                {
                    "id": 1598739662832,
                    "index": 2,
                    "multi_edges": false,
                    "position": 3,
                    "socket_type": 1
                }
            ],
            "outputs": [
                {
                    "id": 1598739664272,
                    "index": 0,
                    "multi_edges": true,
                    "position": 6,
                    "socket_type": 3
                },
                {
                    "id": 1598739662256,
                    "index": 1,
                    "multi_edges": false,
                    "position": 6,
                    "socket_type": 1
                }
            ],
            "content": {
                "Blend": "10",
                "Exponential": "True"
            },
            "op_code": 33,
            "content_label_objname": "kandinsky_cond_interp_node"
        },
        {
            "id": 1598739664080,
            "title": "Kandinsky Conditioning",
            "pos_x": 584.7809082031255,
            "pos_y": -848.9708984374998,
            "inputs": [
                {
                    "id": 1598739665472,
                    "index": 0,
                    "multi_edges": false,
                    "position": 3,
                    "socket_type": 4
                },
                {
                    "id": 1598739663552,
                    "index": 1,
                    "multi_edges": false,
                    "position": 3,
                    "socket_type": 1
                }
            ],
            "outputs": [
                {
                    "id": 1598739664128,
                    "index": 0,
                    "multi_edges": true,
                    "position": 6,
                    "socket_type": 3
                },
                {
                    "id": 1598739665856,
                    "index": 1,
                    "multi_edges": true,
                    "position": 6,
                    "socket_type": 3
                },
                {
                    "id": 1598739664752,
                    "index": 2,
                    "multi_edges": false,
                    "position": 6,
                    "socket_type": 1
                }
            ],
            "content": {
                "Prompt": "highly detailed picture of a cyberpunk megacity",
                "Negative Prompt": "",
                "Guidance Scale": "1.0"
            },
            "op_code": 34,
            "content_label_objname": "kandinsky_cond_node"
        },
        {
            "id": 1598739661920,
            "title": "Kandinsky Conditioning Interpolation",
            "pos_x": 1173.4809082031252,
            "pos_y": -507.98339843749983,
            "inputs": [
                {
                    "id": 1598739665088,
                    "index": 0,
                    "multi_edges": false,
                    "position": 3,
                    "socket_type": 3
                },
                {
                    "id": 1598739663984,
                    "index": 1,
                    "multi_edges": false,
                    "position": 3,
                    "socket_type": 3
                },
                {
                    "id": 1598739661056,
                    "index": 2,
                    "multi_edges": false,
                    "position": 3,
                    "socket_type": 1
                }
            ],
            "outputs": [
                {
                    "id": 1598739666576,
                    "index": 0,
                    "multi_edges": true,
                    "position": 6,
                    "socket_type": 3
                },
                {
                    "id": 1598739203984,
                    "index": 1,
                    "multi_edges": false,
                    "position": 6,
                    "socket_type": 1
                }
            ],
            "content": {
                "Blend": "10",
                "Exponential": "True"
            },
            "op_code": 33,
            "content_label_objname": "kandinsky_cond_interp_node"
        },
        {
            "id": 1598739664656,
            "title": "Image Preview",
            "pos_x": 2266.230908203126,
            "pos_y": -680.2958984374995,
            "inputs": [
                {
                    "id": 1598739211520,
                    "index": 0,
                    "multi_edges": false,
                    "position": 3,
                    "socket_type": 5
                },
                {
                    "id": 1598739206672,
                    "index": 1,
                    "multi_edges": false,
                    "position": 3,
                    "socket_type": 6
                },
                {
                    "id": 1598739207488,
                    "index": 2,
                    "multi_edges": false,
                    "position": 3,
                    "socket_type": 1
                }
            ],
            "outputs": [
                {
                    "id": 1598739603728,
                    "index": 0,
                    "multi_edges": true,
                    "position": 6,
                    "socket_type": 5
                },
                {
                    "id": 1598739603824,
                    "index": 1,
                    "multi_edges": true,
                    "position": 6,
                    "socket_type": 6
                },
                {
                    "id": 1598739602288,
                    "index": 2,
                    "multi_edges": false,
                    "position": 6,
                    "socket_type": 1
                }
            ],
            "content": {
                "FPS": "24",
                "": "True"
            },
            "op_code": 28,
            "content_label_objname": "image_output_node"
        },
        {
            "id": 1598739206240,
            "title": "FILM",
            "pos_x": 2845.615917968749,
            "pos_y": -489.3908691406247,
            "inputs": [
                {
                    "id": 1598739206816,
                    "index": 0,
                    "multi_edges": false,
                    "position": 3,
                    "socket_type": 5
                },
                {
                    "id": 1598739207344,
                    "index": 1,
                    "multi_edges": false,
                    "position": 3,
                    "socket_type": 5
                },
                {
                    "id": 1598739207920,
                    "index": 2,
                    "multi_edges": false,
                    "position": 3,
                    "socket_type": 1
                }
            ],
            "outputs": [
                {
                    "id": 1598739207968,
                    "index": 0,
                    "multi_edges": true,
                    "position": 6,
                    "socket_type": 5
                },
                {
                    "id": 1599361738512,
                    "index": 1,
                    "multi_edges": false,
                    "position": 6,
                    "socket_type": 1
                }
            ],
            "content": {
                "FRAMES": "10"
            },
            "op_code": 68,
            "content_label_objname": "FILM_node"
        },
        {
            "id": 1598739202256,
            "title": "Kandinsky Conditioning",
            "pos_x": 588.6059082031253,
            "pos_y": -287.0458984374995,
            "inputs": [
                {
                    "id": 1598739662544,
                    "index": 0,
                    "multi_edges": false,
                    "position": 3,
                    "socket_type": 4
                },
                {
                    "id": 1598739665136,
                    "index": 1,
                    "multi_edges": false,
                    "position": 3,
                    "socket_type": 1
                }
            ],
            "outputs": [
                {
                    "id": 1598739663264,
                    "index": 0,
                    "multi_edges": true,
                    "position": 6,
                    "socket_type": 3
                },
                {
                    "id": 1598739665328,
                    "index": 1,
                    "multi_edges": true,
                    "position": 6,
                    "socket_type": 3
                },
                {
                    "id": 1598739663456,
                    "index": 2,
                    "multi_edges": false,
                    "position": 6,
                    "socket_type": 1
                }
            ],
            "content": {
                "Prompt": "highly detailed picture of a medieval megacity",
                "Negative Prompt": "",
                "Guidance Scale": "1.0"
            },
            "op_code": 34,
            "content_label_objname": "kandinsky_cond_node"
        },
        {
            "id": 1598739663504,
            "title": "Video Save",
            "pos_x": 3219.564892578123,
            "pos_y": -529.1491699218748,
            "inputs": [
                {
                    "id": 1598701682592,
                    "index": 0,
                    "multi_edges": false,
                    "position": 3,
                    "socket_type": 5
                },
                {
                    "id": 1598701674576,
                    "index": 1,
                    "multi_edges": false,
                    "position": 3,
                    "socket_type": 1
                }
            ],
            "outputs": [
                {
                    "id": 1598701674480,
                    "index": 0,
                    "multi_edges": true,
                    "position": 6,
                    "socket_type": 5
                },
                {
                    "id": 1598701667808,
                    "index": 1,
                    "multi_edges": false,
                    "position": 6,
                    "socket_type": 1
                }
            ],
            "content": {
                "Save Format": "mp4_ffmpeg",
                "Width": "512",
                "Height": "512",
                "FPS": "30",
                "Dump at every:": "0",
                "Audio Path:": "",
                "Keep Buffer": "False"
            },
            "op_code": 36,
            "content_label_objname": "video_output_node"
        },
        {
            "id": 1598739665280,
            "title": "Kandinsky Sampler",
            "pos_x": 1787.1509082031248,
            "pos_y": -989.0158984374993,
            "inputs": [
                {
                    "id": 1598739600320,
                    "index": 0,
                    "multi_edges": false,
                    "position": 3,
                    "socket_type": 4
                },
                {
                    "id": 1598739601520,
                    "index": 1,
                    "multi_edges": false,
                    "position": 3,
                    "socket_type": 3
                },
                {
                    "id": 1598739602672,
                    "index": 2,
                    "multi_edges": false,
                    "position": 3,
                    "socket_type": 3
                },
                {
                    "id": 1598739603872,
                    "index": 3,
                    "multi_edges": false,
                    "position": 3,
                    "socket_type": 4
                },
                {
                    "id": 1598739603968,
                    "index": 4,
                    "multi_edges": false,
                    "position": 3,
                    "socket_type": 5
                },
                {
                    "id": 1598739601232,
                    "index": 5,
                    "multi_edges": false,
                    "position": 3,
                    "socket_type": 1
                }
            ],
            "outputs": [
                {
                    "id": 1598739600656,
                    "index": 0,
                    "multi_edges": true,
                    "position": 6,
                    "socket_type": 5
                },
                {
                    "id": 1598739604016,
                    "index": 1,
                    "multi_edges": false,
                    "position": 6,
                    "socket_type": 1
                }
            ],
            "content": {
                "Seed:": "",
                "Steps:": "75",
                "Guidance Scale:": "4.0",
                "Strength:": "0.25",
                "Width:": "768",
                "Height:": "512",
                "Image Feedback": "False"
            },
            "op_code": 38,
            "content_label_objname": "kandinsky_sampler_node"
        }
    ],
    "edges": [
        {
            "id": 1598739601568,
            "edge_type": 2,
            "start": 1599340193408,
            "end": 1598739662544
        },
        {
            "id": 1598739604256,
            "edge_type": 2,
            "start": 1598739662256,
            "end": 1598739601232
        },
        {
            "id": 1598739602912,
            "edge_type": 2,
            "start": 1599340183712,
            "end": 1598739600320
        },
        {
            "id": 1598739603536,
            "edge_type": 2,
            "start": 1598701674576,
            "end": 1599361738512
        },
        {
            "id": 1598739602960,
            "edge_type": 2,
            "start": 1598739604016,
            "end": 1598739207488
        },
        {
            "id": 1598739603344,
            "edge_type": 2,
            "start": 1598739665472,
            "end": 1599340193408
        },
        {
            "id": 1598739602000,
            "edge_type": 2,
            "start": 1598739207968,
            "end": 1598701682592
        },
        {
            "id": 1598739603056,
            "edge_type": 2,
            "start": 1598739663456,
            "end": 1598739661056
        },
        {
            "id": 1598739601472,
            "edge_type": 2,
            "start": 1598739207920,
            "end": 1598739602288
        },
        {
            "id": 1598739604640,
            "edge_type": 2,
            "start": 1598739664752,
            "end": 1598739665136
        },
        {
            "id": 1598739604592,
            "edge_type": 2,
            "start": 1598739664272,
            "end": 1598739602672
        },
        {
            "id": 1598739600800,
            "edge_type": 2,
            "start": 1598739666576,
            "end": 1598739601520
        },
        {
            "id": 1598739596480,
            "edge_type": 2,
            "start": 1598739663984,
            "end": 1598739664128
        },
        {
            "id": 1598739602384,
            "edge_type": 2,
            "start": 1598739203984,
            "end": 1598739662832
        },
        {
            "id": 1598739662592,
            "edge_type": 2,
            "start": 1599354925888,
            "end": 1598739663552
        },
        {
            "id": 1598739663312,
            "edge_type": 2,
            "start": 1598739662640,
            "end": 1598739665856
        },
        {
            "id": 1598739666480,
            "edge_type": 2,
            "start": 1598739665328,
            "end": 1598739664560
        },
        {
            "id": 1598739665760,
            "edge_type": 2,
            "start": 1598739603728,
            "end": 1598739207344
        },
        {
            "id": 1598739599936,
            "edge_type": 2,
            "start": 1598739663264,
            "end": 1598739665088
        },
        {
            "id": 1598739599984,
            "edge_type": 2,
            "start": 1598739600656,
            "end": 1598739211520
        },
        {
            "id": 1598739601328,
            "edge_type": 2,
            "start": 1598739603872,
            "end": 1599340190000
        }
    ]
}